spiakid_DRS/DRSterm.py
spiakid_DRS/Home.py
spiakid_DRS/__init__.py
spiakid_DRS/inter.py
spiakid_DRS/recons_inter.py
spiakid_DRS/SpectralRes/Data.py
spiakid_DRS/SpectralRes/Detect.py
spiakid_DRS/SpectralRes/IQCalibration.py
spiakid_DRS/SpectralRes/Plot.py
spiakid_DRS/SpectralRes/__init__.py
spiakid_DRS/SpectralRes/cmplxIQ.py
spiakid_DRS/SpectralRes/fun.py
spiakid_DRS/SpectralRes/resonator.py
spiakid_DRS/SpectralRes/utility.py
spiakid_DRS/pages/DataAnalysis.py
spiakid_DRS/pages/Simulation.py
spiakid_DRS/pages/__init__.py
spiakid_DRS/pages/Sim_func/FITS_read.py
spiakid_DRS/pages/Sim_func/Fits_write.py
spiakid_DRS/pages/Sim_func/Sim_creation.py
spiakid_DRS/pages/Sim_func/Test.py
spiakid_DRS/pages/Sim_func/WvConv.py
spiakid_DRS/pages/Sim_func/Yaml_write.py
spiakid_DRS/pages/Sim_func/__init__.py
spiakid_drs-1.24.dist-info/LICENSE
spiakid_drs-1.24.dist-info/METADATA
spiakid_drs-1.24.dist-info/WHEEL
spiakid_drs-1.24.dist-info/top_level.txt
spiakid_drs-1.24.dist-info/RECORD
