Metadata-Version: 2.1
Name: spiakid-drs
Version: 1.24
Summary: Data Reduction System of SPIAKID project
Author-email: Pasquale Panuzzo <pasquale.panuzzo@gmail.com>
Project-URL: Homepage, https://spiakid.pages.obspm.fr/DRS/index.html
Classifier: Programming Language :: Python :: 3
Classifier: Operating System :: OS Independent
Requires-Python: >=3.7
License-File: LICENSE
Requires-Dist: dynaconf
Requires-Dist: h5py
Requires-Dist: scraps
Requires-Dist: lmfit
Requires-Dist: streamlit
Requires-Dist: pyYAML
